cogs/sona/abc.py
d_snek_cogs_sona-0.0.2.dist-info/METADATA
d_snek_cogs_sona-0.0.2.dist-info/WHEEL
d_snek_cogs_sona-0.0.2.dist-info/top_level.txt
d_snek_cogs_sona-0.0.2.dist-info/RECORD
