Metadata-Version: 2.1
Name: d-snek-cogs-sona
Version: 0.0.2
Summary: Discord SNEK Cog; Sona ABC
Home-page: https://git.jboi.dev/ShadowJonathan/snek-sona
Author: Jonathan de Jong
Author-email: jonathan@automatia.nl
License: UNKNOWN
Platform: UNKNOWN
Classifier: Programming Language :: Python :: 3
Classifier: License :: OSI Approved :: MIT License
Classifier: Operating System :: OS Independent
Requires-Python: >=3.6
Requires-Dist: d-snek (>=1.2.4)
Requires-Dist: discord.py (>=1.2.5)
Provides-Extra: dev
Requires-Dist: ipython ; extra == 'dev'
Requires-Dist: twine ; extra == 'dev'
